pyclang/__init__.py
pyclang/cli_ext.py
pyclang/idf_extension.py
pyclang/runner.py
pyclang/utils.py
pyclang/scripts/__init__.py
pyclang/scripts/idf_clang_tidy.py
pyclang-0.6.0.dist-info/LICENSE
pyclang-0.6.0.dist-info/METADATA
pyclang-0.6.0.dist-info/WHEEL
pyclang-0.6.0.dist-info/entry_points.txt
pyclang-0.6.0.dist-info/top_level.txt
pyclang-0.6.0.dist-info/RECORD
